Metadata-Version: 1.1
Name: newpyfile
Version: 0.0.2
Summary: Create .py files from your cli.
Home-page: https://github.com/monzita/newpyfile
Author: Monika Ilieva
Author-email: hidden@hidden.com
License: MIT
Keywords: newpyfile file python
Platform: UNKNOWN
Classifier: Development Status :: 3 - Alpha
Classifier: Environment :: Console
Classifier: Programming Language :: Python :: 3.8
Classifier: License :: OSI Approved :: MIT License
